trivial_package/__init__.py
trivial_package/test.py
test_upload_fraianna-0.0.2.dist-info/LICENSE
test_upload_fraianna-0.0.2.dist-info/METADATA
test_upload_fraianna-0.0.2.dist-info/WHEEL
test_upload_fraianna-0.0.2.dist-info/top_level.txt
test_upload_fraianna-0.0.2.dist-info/RECORD
