Metadata-Version: 2.1
Name: test-upload-fraianna
Version: 0.0.2
Summary: short package description
Home-page: https://github.com/
Author: author
Author-email: author@example.com
License: UNKNOWN
Platform: UNKNOWN
Classifier: Programming Language :: Python :: 3
Classifier: License :: OSI Approved :: MIT License
Classifier: Operating System :: OS Independent
Requires-Python: >=3.6
License-File: LICENSE
